[{"id":1,"key":32324324,"access":1},{"id":2,"key":21003242,"access":0},{"id":3,"key":815322,"access":0},{"id":4,"key":63074,"access":1},{"id":5,"key":123456,"access":0},{"id":6,"key":666666422,"access":1},{"id":7,"key":77777722,"access":0},{"id":8,"key":109262,"access":1},{"id":9,"key":80768,"access":1},{"id":10,"key":688638,"access":1},{"id":11,"key":0,"access":1},{"id":12,"key":601031,"access":1},{"id":13,"key":659220,"access":1},{"id":14,"key":432639,"access":1},{"id":15,"key":175569,"access":1},{"id":16,"key":271121,"access":1},{"id":17,"key":437503235,"access":0},{"id":18,"key":652430,"access":0},{"id":19,"key":479691,"access":0},{"id":20,"key":520390,"access":0},{"id":21,"key":309797,"access":1},{"id":22,"key":409411,"access":1},{"id":23,"key":688175,"access":0},{"id":24,"key":830501,"access":0},{"id":25,"key":10280574,"access":1},{"id":26,"key":987058,"access":0},{"id":27,"key":229886,"access":0},{"id":28,"key":611897,"access":1},{"id":29,"key":321508,"access":1},{"id":30,"key":922633,"access":1},{"id":31,"key":285900,"access":0},{"id":32,"key":848366,"access":1},{"id":33,"key":915229,"access":0},{"id":34,"key":419880,"access":1},{"id":35,"key":307514,"access":0},{"id":36,"key":920501,"access":1},{"id":37,"key":293961,"access":0},{"id":38,"key":992924,"access":0},{"id":39,"key":199211,"access":1},{"id":40,"key":594320,"access":0},{"id":41,"key":674159,"access":0},{"id":42,"key":416974,"access":0},{"id":43,"key":314247,"access":1},{"id":44,"key":151800,"access":0},{"id":45,"key":930386,"access":1},{"id":46,"key":590347,"access":1},{"id":47,"key":969648,"access":1},{"id":48,"key":442400,"access":1},{"id":49,"key":548408,"access":1},{"id":50,"key":371041,"access":0},{"id":51,"key":952225,"access":1},{"id":52,"key":368651,"access":1},{"id":53,"key":937788,"access":1},{"id":54,"key":398106,"access":0},{"id":55,"key":66441653,"access":1},{"id":56,"key":489505,"access":0},{"id":57,"key":540633,"access":0},{"id":58,"key":744527,"access":1},{"id":59,"key":490128,"access":1},{"id":60,"key":210904,"access":0},{"id":61,"key":603744,"access":0},{"id":62,"key":734982,"access":0},{"id":63,"key":502183,"access":0},{"id":64,"key":836259,"access":0},{"id":65,"key":224807,"access":0},{"id":66,"key":745015,"access":1},{"id":67,"key":779158,"access":0},{"id":68,"key":500366,"access":0},{"id":69,"key":855271,"access":0},{"id":70,"key":12131412,"access":1}]